brainframe/cli/__init__.py
brainframe/cli/brainframe_compose.py
brainframe/cli/brainframe_shell.py
brainframe/cli/commands/__init__.py
brainframe/cli/commands/backup.py
brainframe/cli/commands/compose.py
brainframe/cli/commands/info.py
brainframe/cli/commands/install.py
brainframe/cli/commands/self_update.py
brainframe/cli/commands/shell.py
brainframe/cli/commands/uninstall.py
brainframe/cli/commands/update.py
brainframe/cli/commands/utils.py
brainframe/cli/config.py
brainframe/cli/defaults.yaml
brainframe/cli/dependencies.py
brainframe/cli/frozen_utils.py
brainframe/cli/main.py
brainframe/cli/os_utils.py
brainframe/cli/print_utils.py
brainframe/cli/translations/backup.en.yml
brainframe/cli/translations/general.en.yml
brainframe/cli/translations/info.en.yml
brainframe/cli/translations/install.en.yml
brainframe/cli/translations/portal.en.yml
brainframe/cli/translations/self-update.en.yml
brainframe/cli/translations/shell.en.yml
brainframe/cli/translations/uninstall.en.yml
brainframe/cli/translations/update.en.yml
brainframe_cli-0.3.2.dist-info/COPYING
brainframe_cli-0.3.2.dist-info/METADATA
brainframe_cli-0.3.2.dist-info/WHEEL
brainframe_cli-0.3.2.dist-info/entry_points.txt
brainframe_cli-0.3.2.dist-info/RECORD
