Metadata-Version: 2.1
Name: brainframe-cli
Version: 0.3.2
Summary: Makes installing and managing a BrainFrame server easy
Home-page: https://github.com/aotuai/brainframe_cli
License: BSD-3-Clause
Author: Aotu.ai
Author-email: info@aotu.ai
Requires-Python: >=3.10,<4.0
Classifier: License :: OSI Approved :: BSD License
Classifier: Programming Language :: Python :: 3
Classifier: Programming Language :: Python :: 3.10
Classifier: Programming Language :: Python :: 3.11
Classifier: Programming Language :: Python :: 3.12
Requires-Dist: distro (>=1.5,<2.0)
Requires-Dist: docker (>4.3.1,<7.0.0)
Requires-Dist: packaging (>=20.4,<21.0)
Requires-Dist: python-i18n (>=0.3,<0.4)
Requires-Dist: pyyaml (>=6.0)
Requires-Dist: requests (>=2.24.0,<3.0.0)
Requires-Dist: websocket-client (>=0.32.0,<1.0)
Project-URL: Repository, https://github.com/aotuai/brainframe_cli
